<?xml version="1.0" encoding="utf-8" ?><dwsync><file name="404.php" server="50.63.220.1" local="3462567850" remote="319519907866598860" Dst="-1" /><file name="archive.php" server="50.63.220.1" local="3462567850" remote="319519907866598860" Dst="-1" /><file name="author.php" server="50.63.220.1" local="3465518360" remote="319519907866598860" Dst="-1" /><file name="category.php" server="50.63.220.1" local="3462567850" remote="319519907866598860" Dst="-1" /><file name="comments.php" server="50.63.220.1" local="3464213950" remote="319519907866598860" Dst="-1" /><file name="content-aside.php" server="50.63.220.1" local="3450117450" remote="319519907866598860" Dst="-1" /><file name="content-image.php" server="50.63.220.1" local="3450117450" remote="319519907866598860" Dst="-1" /><file name="content-link.php" server="50.63.220.1" local="3434156746" remote="319519907866598860" Dst="-1" /><file name="content-none.php" server="50.63.220.1" local="3462567850" remote="319519907866598860" Dst="-1" /><file name="content-page.php" server="50.63.220.1" local="3445019434" remote="319519907866598860" Dst="-1" /><file name="content-quote.php" server="50.63.220.1" local="3434156746" remote="319519907866598860" Dst="-1" /><file name="content-status.php" server="50.63.220.1" local="3462567850" remote="319519907866598860" Dst="-1" /><file name="content.php" server="50.63.220.1" local="3465518360" remote="319519907866598860" Dst="-1" /><file name="editor-style-rtl.css" server="50.63.220.1" local="3434156746" remote="319519907866598860" Dst="-1" /><file name="editor-style.css" server="50.63.220.1" local="3452112642" remote="319519907866598860" Dst="-1" /><file name="footer.php" server="50.63.220.1" local="3462567850" remote="319519907866598860" Dst="-1" /><file name="functions.php" server="50.63.220.1" local="3465530992" remote="319519907866598860" Dst="-1" /><file name="header.php" server="50.63.220.1" local="3464843410" remote="319519907866598860" Dst="-1" /><file name="image.php" server="50.63.220.1" local="3464213950" remote="319519907866598860" Dst="-1" /><file name="index.php" server="50.63.220.1" local="3462567850" remote="319519907866598860" Dst="-1" /><file name="page.php" server="50.63.220.1" local="3462567850" remote="319519907866598860" Dst="-1" /><file name="rtl.css" server="50.63.220.1" local="3446232876" remote="319519907866598860" Dst="-1" /><file name="search.php" server="50.63.220.1" local="3462567850" remote="319519907866598860" Dst="-1" /><file name="sidebar.php" server="50.63.220.1" local="3462567850" remote="319519907866598860" Dst="-1" /><file name="sidebar-front.php" server="50.63.220.1" local="3464213950" remote="319519907866598860" Dst="-1" /><file name="screenshot.png" server="50.63.220.1" local="3469230430" remote="319519907866598860" Dst="-1" /><file name="single.php" server="50.63.220.1" local="3462567850" remote="319519907866598920" Dst="-1" /><file name="style.css" server="50.63.220.1" local="3469159390" remote="319519907866598920" Dst="-1" /><file name="tag.php" server="50.63.220.1" local="3464213950" remote="319519907866598920" Dst="-1" /></dwsync>